rxctl/__init__.py
rxctl/__version__.py
rxctl/bin/__init
rxctl/bin/__run
rxctl/bin/__wait
rxctl/lib/ansible.sh
rxctl/lib/links.py
rxctl/lib/log.py
rxctl/lib/main.py
rxctl/lib/scp.sh
rxctl/lib/utils.py
rxctl-1.0.8.dist-info/METADATA
rxctl-1.0.8.dist-info/WHEEL
rxctl-1.0.8.dist-info/entry_points.txt
rxctl-1.0.8.dist-info/licenses/LICENSE
rxctl-1.0.8.dist-info/RECORD
