Metadata-Version: 2.4
Name: rxctl
Version: 1.0.8
Summary: Linux remote execution tool
License-File: LICENSE
Author: mihaiush
Author-email: mihaiush@gmail.com
Requires-Python: >=3.7,<4.0
Classifier: Programming Language :: Python :: 3
Classifier: Programming Language :: Python :: 3.7
Classifier: Programming Language :: Python :: 3.8
Classifier: Programming Language :: Python :: 3.9
Classifier: Programming Language :: Python :: 3.10
Classifier: Programming Language :: Python :: 3.11
Classifier: Programming Language :: Python :: 3.12
Classifier: Programming Language :: Python :: 3.13
Classifier: Programming Language :: Python :: 3.14
Requires-Dist: click
Requires-Dist: prettytable
Project-URL: Homepage, https://github.com/mihaiush/rxctl
